DLMS_SPODES_client/FCS16.py
DLMS_SPODES_client/__init__.py
DLMS_SPODES_client/client.py
DLMS_SPODES_client/logger.py
DLMS_SPODES_client/py.typed
DLMS_SPODES_client/services.py
DLMS_SPODES_client/session.py
DLMS_SPODES_client/settings.py
DLMS_SPODES_client/task.py
DLMS_SPODES_client/gurux_common/enums/TraceLevel.py
DLMS_SPODES_client/gurux_common/enums/__init__.py
DLMS_SPODES_client/gurux_dlms/AesGcmParameter.py
DLMS_SPODES_client/gurux_dlms/CountType.py
DLMS_SPODES_client/gurux_dlms/GXByteBuffer.py
DLMS_SPODES_client/gurux_dlms/GXCiphering.py
DLMS_SPODES_client/gurux_dlms/GXDLMS.py
DLMS_SPODES_client/gurux_dlms/GXDLMSChippering.py
DLMS_SPODES_client/gurux_dlms/GXDLMSChipperingStream.py
DLMS_SPODES_client/gurux_dlms/GXDLMSConfirmedServiceError.py
DLMS_SPODES_client/gurux_dlms/GXDLMSException.py
DLMS_SPODES_client/gurux_dlms/GXDLMSLNParameters.py
DLMS_SPODES_client/gurux_dlms/GXDLMSSNParameters.py
DLMS_SPODES_client/gurux_dlms/GXDLMSSettings.py
DLMS_SPODES_client/gurux_dlms/GXReplyData.py
DLMS_SPODES_client/gurux_dlms/HdlcControlFrame.py
DLMS_SPODES_client/gurux_dlms/MBusCommand.py
DLMS_SPODES_client/gurux_dlms/MBusEncryptionMode.py
DLMS_SPODES_client/gurux_dlms/ResponseType.py
DLMS_SPODES_client/gurux_dlms/SetResponseType.py
DLMS_SPODES_client/gurux_dlms/_HDLCInfo.py
DLMS_SPODES_client/gurux_dlms/__init__.py
DLMS_SPODES_client/gurux_dlms/enums/Access.py
DLMS_SPODES_client/gurux_dlms/enums/ApplicationReference.py
DLMS_SPODES_client/gurux_dlms/enums/Authentication.py
DLMS_SPODES_client/gurux_dlms/enums/BerType.py
DLMS_SPODES_client/gurux_dlms/enums/Command.py
DLMS_SPODES_client/gurux_dlms/enums/Definition.py
DLMS_SPODES_client/gurux_dlms/enums/ErrorCode.py
DLMS_SPODES_client/gurux_dlms/enums/ExceptionServiceError.py
DLMS_SPODES_client/gurux_dlms/enums/HardwareResource.py
DLMS_SPODES_client/gurux_dlms/enums/HdlcFrameType.py
DLMS_SPODES_client/gurux_dlms/enums/Initiate.py
DLMS_SPODES_client/gurux_dlms/enums/LoadDataSet.py
dlms_spodes_client-0.19.29.dist-info/METADATA
dlms_spodes_client-0.19.29.dist-info/WHEEL
dlms_spodes_client-0.19.29.dist-info/entry_points.txt
dlms_spodes_client-0.19.29.dist-info/top_level.txt
dlms_spodes_client-0.19.29.dist-info/RECORD
