Metadata-Version: 2.4
Name: DLMS_SPODES_client
Version: 0.19.29
Summary: dlms-spodes
Author-email: Serj Kotilevski <youserj@outlook.com>
Project-URL: Source, https://github.com/youserj/SPODESclient_prj
Keywords: dlms,spodes,client
Classifier: Programming Language :: Python :: 3
Classifier: License :: OSI Approved :: MIT License
Classifier: Operating System :: OS Independent
Requires-Python: >=3.12
Requires-Dist: pydantic>=2.11
Requires-Dist: pycryptodomex>=3.22.0
Requires-Dist: semver>=3.0
Requires-Dist: StructResult<0.10,>=0.9.2
Requires-Dist: DLMS-SPODES-communications<1.6,>=1.5.4
Requires-Dist: DLMS_SPODES<0.88,>=0.87.8
Requires-Dist: DLMSadapter<0.8,>=0.7.6
Requires-Dist: DLMSCommunicationProfile<0.2,>=0.1.11
Requires-Dist: numpy>=2.3.2
Provides-Extra: dev
Requires-Dist: mypy>=1.5.0; extra == "dev"
Requires-Dist: ruff>=0.11; extra == "dev"
Requires-Dist: types-requests; extra == "dev"
Requires-Dist: build; extra == "dev"
Requires-Dist: twine; extra == "dev"
